api_monitor/__init__.py
api_monitor/admin.py
api_monitor/apps.py
api_monitor/middleware.py
api_monitor/models.py
api_monitor/urls.py
api_monitor/views.py
api_monitor/migrations/__init__.py
api_monitor/templates/urls.py
api_monitor/templates/utils.py
api_monitor/templates/views.py
api_monitor/utils/__init__.py
api_monitor/utils/charts.py
api_monitor/utils/dashboard.py
api_monitor/utils/types.py
django_api_monitor-0.1.1.dist-info/METADATA
django_api_monitor-0.1.1.dist-info/WHEEL
django_api_monitor-0.1.1.dist-info/top_level.txt
django_api_monitor-0.1.1.dist-info/RECORD
