Metadata-Version: 2.4
Name: django-api-monitor
Version: 0.1.1
Summary: Reusable Django app for monitoring API usage and security.
Author: anirudh_mk
License: MIT
Classifier: Framework :: Django
Classifier: Programming Language :: Python
Classifier: License :: OSI Approved :: MIT License
Requires-Dist: Django>=3.2
Requires-Dist: psutil
Dynamic: author
Dynamic: classifier
Dynamic: license
Dynamic: requires-dist
Dynamic: summary
